{
  "type": "elementalamulets:elemental_combination",
  "elemental": {
    "item": "elementalamulets:elemental_shards"
  },
  "ingredients": [
    {
      "tag": "elementalamulets:water_element_convertible"
    },
    {
      "tag": "elementalamulets:water_element_convertible"
    },
    {
      "tag": "elementalamulets:water_element_convertible"
    },
    {
      "tag": "elementalamulets:water_element_convertible"
    },
    {
      "tag": "elementalamulets:water_element_convertible"
    },
    {
      "tag": "elementalamulets:water_element_convertible"
    },
    {
      "tag": "elementalamulets:water_element_convertible"
    },
    {
      "tag": "elementalamulets:water_element_convertible"
    }
  ],
  "result": {
    "item": "elementalamulets:water_element"
  }
}